LICENSE
asan/__init__.py
asan-0.0.1.dist-info/LICENSE
asan-0.0.1.dist-info/WHEEL
asan-0.0.1.dist-info/METADATA
asan-0.0.1.dist-info/RECORD
